shotoapi/__init__.py
shotoapi-0.0.1.dist-info/LICENSE
shotoapi-0.0.1.dist-info/METADATA
shotoapi-0.0.1.dist-info/WHEEL
shotoapi-0.0.1.dist-info/top_level.txt
shotoapi-0.0.1.dist-info/RECORD
